fizz/__init__.py
fizz/fizz.py
fizz-4.2.0.dist-info/LICENSE
fizz-4.2.0.dist-info/METADATA
fizz-4.2.0.dist-info/WHEEL
fizz-4.2.0.dist-info/top_level.txt
fizz-4.2.0.dist-info/RECORD
